pyqiwi/__init__.py
pyqiwi/client.py
pyqiwi/compat.py
pyqiwi-0.2.0.dist-info/DESCRIPTION.rst
pyqiwi-0.2.0.dist-info/METADATA
pyqiwi-0.2.0.dist-info/RECORD
pyqiwi-0.2.0.dist-info/WHEEL
pyqiwi-0.2.0.dist-info/metadata.json
pyqiwi-0.2.0.dist-info/top_level.txt
